cdk_tutor/__init__.py
cdk_tutor/cli.py
cdk_tutor/challenges/__init__.py
cdk_tutor/challenges/sample_challenges.py
cdk_tutor/grader/__init__.py
cdk_tutor/grader/cdk_runner.py
cdk_tutor/grader/cf_comparator.py
cdk_tutor-0.2.0.dist-info/METADATA
cdk_tutor-0.2.0.dist-info/WHEEL
cdk_tutor-0.2.0.dist-info/entry_points.txt
cdk_tutor-0.2.0.dist-info/RECORD
