Metadata-Version: 2.4
Name: cdk-tutor
Version: 0.2.0
Summary: A CLI application that teaches AWS CDK in Python to software engineers.
Project-URL: Homepage, https://github.com/amirkarimi/cdk-tutor
Classifier: Intended Audience :: Developers
Classifier: License :: OSI Approved :: MIT License
Classifier: Operating System :: OS Independent
Classifier: Programming Language :: Python :: 3
Classifier: Topic :: Software Development :: Build Tools
Requires-Python: >=3.9
Requires-Dist: aws-cdk-lib>=2.0.0
Requires-Dist: deepdiff>=6.0.0
Requires-Dist: pydantic>=2.0.0
Requires-Dist: pytest>=8.3.5
Requires-Dist: pyyaml>=6.0
Requires-Dist: rich>=13.7.0
Requires-Dist: typer>=0.9.0
Provides-Extra: dev
Requires-Dist: black>=23.0.0; extra == 'dev'
Requires-Dist: isort>=5.0.0; extra == 'dev'
Requires-Dist: mypy>=1.0.0; extra == 'dev'
Requires-Dist: pytest>=7.0.0; extra == 'dev'
